chaospixie/__init__.py
chaospixie/probes.py
chaospixie/tolerances.py
chaostoolkit_pixie-0.1.1.dist-info/LICENSE
chaostoolkit_pixie-0.1.1.dist-info/METADATA
chaostoolkit_pixie-0.1.1.dist-info/WHEEL
chaostoolkit_pixie-0.1.1.dist-info/top_level.txt
chaostoolkit_pixie-0.1.1.dist-info/RECORD
